apl/__init__.py
apl/__version__.py
apl/acquisitions.py
apl/apl.py
apl/gaussian_process.py
apl/posterior_approximation.py
apl/utils.py
APL_Brochu-0.0.1.dist-info/LICENSE
APL_Brochu-0.0.1.dist-info/METADATA
APL_Brochu-0.0.1.dist-info/WHEEL
APL_Brochu-0.0.1.dist-info/top_level.txt
APL_Brochu-0.0.1.dist-info/RECORD
