Metadata-Version: 2.1
Name: APL-Brochu
Version: 0.0.1
Summary: APL-Brochu - The Implementation of the paper Active Preference Learning with Discrete Choice Data by Brochu et al. (2011)
Home-page: https://github.com/dorukhansergin/APL-Brochu
Author: N. Dorukhan Sergin
Author-email: dorukhan.sergin@gmail.com
License: UNKNOWN
Platform: UNKNOWN
Requires-Dist: numpy (<2.0.0,~=1.20)
Requires-Dist: scikit-learn (<1.0.0,~=0.24.1)
Requires-Dist: scipy
Provides-Extra: dev
Requires-Dist: pytest ; extra == 'dev'
Requires-Dist: pylint ; extra == 'dev'
Requires-Dist: black ; extra == 'dev'
Requires-Dist: rope ; extra == 'dev'
Provides-Extra: extras
Requires-Dist: streamlit ; extra == 'extras'
Requires-Dist: matplotlib ; extra == 'extras'
Requires-Dist: plotly ; extra == 'extras'
